fast_deep_rnn/__init__.py
fast_deep_rnn/_modidx.py
fast_deep_rnn/common_core.py
fast_deep_rnn/core.py
fast_deep_rnn/core_v2.py
fast_deep_rnn/sort_training.py
fast_deep_rnn/old/__init__.py
fast_deep_rnn/old/core.py
fast_deep_rnn-0.0.2.dist-info/LICENSE
fast_deep_rnn-0.0.2.dist-info/METADATA
fast_deep_rnn-0.0.2.dist-info/WHEEL
fast_deep_rnn-0.0.2.dist-info/entry_points.txt
fast_deep_rnn-0.0.2.dist-info/top_level.txt
fast_deep_rnn-0.0.2.dist-info/RECORD
