Metadata-Version: 2.1
Name: fast-deep-rnn
Version: 0.0.2
Summary: Deep Learning framework extension allowing more efficient backpropogation of gradient in a situation with branched computational graph structure
Home-page: https://github.com/Hacker1337/fast-deep-rnn
Author: Hacker1337
Author-email: amirfvb@gmail.com
License: Apache Software License 2.0
Keywords: nbdev jupyter notebook python
Classifier: Development Status :: 4 - Beta
Classifier: Intended Audience :: Developers
Classifier: Natural Language :: English
Classifier: Programming Language :: Python :: 3.7
Classifier: Programming Language :: Python :: 3.8
Classifier: Programming Language :: Python :: 3.9
Classifier: Programming Language :: Python :: 3.10
Classifier: License :: OSI Approved :: Apache Software License
Requires-Python: >=3.7
License-File: LICENSE
Requires-Dist: ipykernel
Requires-Dist: numpy
Requires-Dist: pandas
Requires-Dist: matplotlib
Requires-Dist: scikit-learn
Requires-Dist: lets-plot
Provides-Extra: dev
Requires-Dist: nbdev ; extra == 'dev'
